README.md
setup.cfg
setup.py
src/color.py
src/config.py
src/const.py
src/files.py
src/kiqpo
src/web.py
src/kiqpo.egg-info/PKG-INFO
src/kiqpo.egg-info/SOURCES.txt
src/kiqpo.egg-info/dependency_links.txt
src/kiqpo.egg-info/requires.txt
src/kiqpo.egg-info/top_level.txt