Metadata-Version: 2.1
Name: kiqpo
Version: 3
Summary: UNKNOWN
Home-page: https://github.com/kiqpo
Author: Shajin
Author-email: shajin.sha10@gmail.com
License: MIT
Keywords: Kiqpo,ui,ux,web
Platform: UNKNOWN
Classifier: Development Status :: 3 - Alpha
Classifier: Intended Audience :: Developers
Classifier: Topic :: Software Development :: Build Tools
Classifier: License :: OSI Approved :: MIT License
Classifier: Programming Language :: Python :: 3
Classifier: Programming Language :: Python :: 3.4
Classifier: Programming Language :: Python :: 3.5
Classifier: Programming Language :: Python :: 3.6
